README.md
setup.py
cloudmersive_currency_api_client/__init__.py
cloudmersive_currency_api_client/api_client.py
cloudmersive_currency_api_client/configuration.py
cloudmersive_currency_api_client/rest.py
cloudmersive_currency_api_client.egg-info/PKG-INFO
cloudmersive_currency_api_client.egg-info/SOURCES.txt
cloudmersive_currency_api_client.egg-info/dependency_links.txt
cloudmersive_currency_api_client.egg-info/requires.txt
cloudmersive_currency_api_client.egg-info/top_level.txt
cloudmersive_currency_api_client/api/__init__.py
cloudmersive_currency_api_client/api/currency_exchange_api.py
cloudmersive_currency_api_client/models/__init__.py
cloudmersive_currency_api_client/models/available_currency.py
cloudmersive_currency_api_client/models/available_currency_response.py
cloudmersive_currency_api_client/models/converted_currency_result.py
cloudmersive_currency_api_client/models/exchange_rate_result.py
test/__init__.py
test/test_available_currency.py
test/test_available_currency_response.py
test/test_converted_currency_result.py
test/test_currency_exchange_api.py
test/test_exchange_rate_result.py