Metadata-Version: 2.1
Name: cloudmersive-currency-api-client
Version: 3.0.1
Summary: currencyapi
Home-page: https://www.cloudmersive.com/currency-api
Author-email: 
License: UNKNOWN
Keywords: Swagger,currencyapi
Platform: UNKNOWN
